azure_functions_worker_v1/__init__.py
azure_functions_worker_v1/functions.py
azure_functions_worker_v1/handle_event.py
azure_functions_worker_v1/loader.py
azure_functions_worker_v1/logging.py
azure_functions_worker_v1/otel.py
azure_functions_worker_v1/version.py
azure_functions_worker_v1/bindings/context.py
azure_functions_worker_v1/bindings/datumdef.py
azure_functions_worker_v1/bindings/generic.py
azure_functions_worker_v1/bindings/meta.py
azure_functions_worker_v1/bindings/nullable_converters.py
azure_functions_worker_v1/bindings/out.py
azure_functions_worker_v1/bindings/retrycontext.py
azure_functions_worker_v1/bindings/tracecontext.py
azure_functions_worker_v1/utils/__init__.py
azure_functions_worker_v1/utils/constants.py
azure_functions_worker_v1/utils/current.py
azure_functions_worker_v1/utils/env_state.py
azure_functions_worker_v1/utils/helpers.py
azure_functions_worker_v1/utils/tracing.py
azure_functions_worker_v1/utils/typing_inspect.py
azure_functions_worker_v1/utils/validators.py
azure_functions_worker_v1/utils/wrappers.py
test_worker_v1-1.0.0a11.dist-info/licenses/LICENSE
tests/protos/__init__.py
tests/protos/identity/__init__.py
tests/protos/shared/__init__.py
tests/unittests/test_handle_event.py
tests/unittests/default_template/__init__.py
tests/unittests/default_template/function.json
tests/utils/__init__.py
tests/utils/testutils.py
test_worker_v1-1.0.0a11.dist-info/METADATA
test_worker_v1-1.0.0a11.dist-info/WHEEL
test_worker_v1-1.0.0a11.dist-info/top_level.txt
test_worker_v1-1.0.0a11.dist-info/RECORD
