Metadata-Version: 2.4
Name: test-worker-v1
Version: 1.0.0a11
License-File: LICENSE
Requires-Dist: azure-functions
Provides-Extra: dev
Requires-Dist: azure-eventhub; extra == "dev"
Requires-Dist: azure-functions-durable; extra == "dev"
Requires-Dist: flask; extra == "dev"
Requires-Dist: fastapi~=0.103.2; extra == "dev"
Requires-Dist: pydantic; extra == "dev"
Requires-Dist: pycryptodome==3.*; extra == "dev"
Requires-Dist: flake8==5.*; python_version == "3.7" and extra == "dev"
Requires-Dist: flake8==6.*; python_version >= "3.8" and extra == "dev"
Requires-Dist: mypy; extra == "dev"
Requires-Dist: pytest~=7.4.4; extra == "dev"
Requires-Dist: requests==2.*; extra == "dev"
Requires-Dist: coverage; extra == "dev"
Requires-Dist: pytest-sugar; extra == "dev"
Requires-Dist: pytest-cov; extra == "dev"
Requires-Dist: pytest-xdist; extra == "dev"
Requires-Dist: pytest-randomly; extra == "dev"
Requires-Dist: pytest-instafail; extra == "dev"
Requires-Dist: pytest-rerunfailures; extra == "dev"
Requires-Dist: ptvsd; extra == "dev"
Requires-Dist: python-dotenv; extra == "dev"
Requires-Dist: plotly; extra == "dev"
Requires-Dist: scikit-learn; extra == "dev"
Requires-Dist: opencv-python; extra == "dev"
Requires-Dist: pandas; extra == "dev"
Requires-Dist: numpy; extra == "dev"
Requires-Dist: pre-commit; extra == "dev"
Requires-Dist: invoke; extra == "dev"
Dynamic: license-file
